grid_pop/__init__.py
grid_pop/datasets/__init__.py
grid_pop/datasets/_base.py
grid_pop/datasets/_gpw_v4_population.py
grid_pop/shapes.py
grid_pop-0.1.1.dist-info/METADATA
grid_pop-0.1.1.dist-info/WHEEL
grid_pop-0.1.1.dist-info/RECORD
