Metadata-Version: 2.1
Name: grid-pop
Version: 0.1.1
Summary: Accessing SEDAC's Gridded Population of the World data.
Home-page: https://github.com/edwardlk/grid-pop
Author: Ed K
Author-email: e.kramkowski@gmail.com
Requires-Python: >=3.9,<4.0
Classifier: Development Status :: 4 - Beta
Classifier: Programming Language :: Python :: 3
Classifier: Programming Language :: Python :: 3.9
Classifier: Programming Language :: Python :: 3.10
Classifier: Programming Language :: Python :: 3.11
Classifier: Programming Language :: Python :: 3.12
Requires-Dist: numpy (>=1.26.3,<2.0.0)
Requires-Dist: requests (>=2.31.0,<3.0.0)
Project-URL: Repository, https://github.com/edwardlk/grid-pop
